flex_evals/__init__.py
flex_evals/constants.py
flex_evals/engine.py
flex_evals/exceptions.py
flex_evals/pytest_decorator.py
flex_evals/registry.py
flex_evals/schema_generator.py
flex_evals/checks/__init__.py
flex_evals/checks/attribute_exists.py
flex_evals/checks/base.py
flex_evals/checks/contains.py
flex_evals/checks/custom_function.py
flex_evals/checks/equals.py
flex_evals/checks/exact_match.py
flex_evals/checks/is_empty.py
flex_evals/checks/llm_judge.py
flex_evals/checks/regex.py
flex_evals/checks/schema.py
flex_evals/checks/semantic_similarity.py
flex_evals/checks/threshold.py
flex_evals/schemas/__init__.py
flex_evals/schemas/check.py
flex_evals/schemas/output.py
flex_evals/schemas/results.py
flex_evals/schemas/test_case.py
flex_evals/utils/__init__.py
flex_evals/utils/jsonpath_resolver.py
flex_evals/utils/schema_validation.py
flex_evals-0.3.22.dist-info/METADATA
flex_evals-0.3.22.dist-info/WHEEL
flex_evals-0.3.22.dist-info/licenses/LICENSE
flex_evals-0.3.22.dist-info/RECORD
