Metadata-Version: 2.4
Name: flex-evals
Version: 0.3.22
Summary: A flexible evaluation framework for testing and validating AI systems, LLMs, and APIs with structured checks and async support
License-File: LICENSE
Requires-Python: >=3.11
Requires-Dist: jsonpath-ng>=1.6.0
Requires-Dist: jsonschema>=4.24.0
Requires-Dist: packaging>=25.0
Requires-Dist: pydantic>=2.11.6
Requires-Dist: python-dotenv>=1.1.0
Requires-Dist: pyyaml>=6.0.2
Requires-Dist: requests>=2.32.4
Requires-Dist: ruamel-yaml>=0.18.14
